{"availableLanguageIds": ["en_US"], "contentType": "journal", "dataDefinitionFields": [{"customProperties": {"labelAtStructureLevel": true, "hideField": false, "confirmationErrorMessage": {"en_US": ""}, "dataType": "string", "tooltip": {"en_US": ""}, "requireConfirmation": false, "displayStyle": "singleline", "requiredErrorMessage": {"en_US": ""}, "visibilityExpression": "", "fieldNamespace": "", "objectFieldName": "", "options": {}, "nativeField": false, "confirmationLabel": {"en_US": ""}, "fieldReference": "FullName", "placeholder": {"en_US": ""}, "direction": ["vertical"]}, "defaultValue": {"en_US": ""}, "fieldType": "text", "indexType": "keyword", "indexable": true, "label": {"en_US": "Full Name"}, "localizable": true, "name": "Text12982626", "nestedDataDefinitionFields": [], "readOnly": false, "repeatable": false, "required": false, "showLabel": true, "tip": {"en_US": ""}}, {"customProperties": {"requiredErrorMessage": {"en_US": ""}, "visibilityExpression": "", "fieldNamespace": "", "objectFieldName": "", "dataType": "image", "requiredDescription": true, "fieldReference": "ProfilePicture"}, "defaultValue": {"en_US": {}}, "fieldType": "image", "indexType": "text", "indexable": true, "label": {"en_US": "Profile Picture"}, "localizable": true, "name": "Image36517163", "nestedDataDefinitionFields": [], "readOnly": false, "repeatable": false, "required": false, "showLabel": true, "tip": {"en_US": ""}}, {"customProperties": {"labelAtStructureLevel": true, "hideField": false, "confirmationErrorMessage": {"en_US": ""}, "dataType": "string", "tooltip": {"en_US": ""}, "requireConfirmation": false, "displayStyle": "singleline", "requiredErrorMessage": {"en_US": ""}, "visibilityExpression": "", "fieldNamespace": "", "objectFieldName": "", "options": {}, "nativeField": false, "confirmationLabel": {"en_US": ""}, "fieldReference": "Designation", "placeholder": {"en_US": ""}, "direction": ["vertical"]}, "defaultValue": {"en_US": ""}, "fieldType": "text", "indexType": "keyword", "indexable": true, "label": {"en_US": "Designation"}, "localizable": true, "name": "Text49810951", "nestedDataDefinitionFields": [], "readOnly": false, "repeatable": false, "required": false, "showLabel": true, "tip": {"en_US": ""}}, {"customProperties": {"labelAtStructureLevel": true, "requiredErrorMessage": {"en_US": ""}, "visibilityExpression": "", "fieldNamespace": "", "objectFieldName": "", "dataType": "date", "nativeField": false, "fieldReference": "JoiningDate"}, "defaultValue": {"en_US": ""}, "fieldType": "date", "indexType": "keyword", "indexable": true, "label": {"en_US": "Joining Date"}, "localizable": true, "name": "Date80926909", "nestedDataDefinitionFields": [], "readOnly": false, "repeatable": false, "required": false, "showLabel": true, "tip": {"en_US": ""}}, {"customProperties": {"labelAtStructureLevel": true, "hideField": false, "confirmationErrorMessage": {"en_US": ""}, "dataType": "string", "tooltip": {"en_US": ""}, "requireConfirmation": false, "displayStyle": "singleline", "requiredErrorMessage": {"en_US": ""}, "visibilityExpression": "", "fieldNamespace": "", "objectFieldName": "", "options": {}, "nativeField": false, "confirmationLabel": {"en_US": ""}, "fieldReference": "ShortDescription", "placeholder": {"en_US": ""}, "direction": ["vertical"]}, "defaultValue": {"en_US": ""}, "fieldType": "text", "indexType": "keyword", "indexable": true, "label": {"en_US": "Short Description"}, "localizable": true, "name": "Text57935359", "nestedDataDefinitionFields": [], "readOnly": false, "repeatable": false, "required": false, "showLabel": true, "tip": {"en_US": ""}}, {"customProperties": {"requiredErrorMessage": {"en_US": ""}, "visibilityExpression": "", "fieldNamespace": "", "objectFieldName": "", "editorConfig": null, "dataType": "string", "fieldReference": "RichText43264232"}, "defaultValue": {"en_US": ""}, "fieldType": "rich_text", "indexType": "text", "indexable": true, "label": {"en_US": "Full Description"}, "localizable": true, "name": "RichText16440602", "nestedDataDefinitionFields": [], "readOnly": false, "repeatable": false, "required": false, "showLabel": true, "tip": {"en_US": ""}}], "dataDefinitionKey": "36917", "defaultDataLayout": {"dataLayoutFields": {}, "dataLayoutPages": [{"dataLayoutRows": [{"dataLayoutColumns": [{"columnSize": 12, "fieldNames": ["Text12982626"]}]}, {"dataLayoutColumns": [{"columnSize": 12, "fieldNames": ["Image36517163"]}]}, {"dataLayoutColumns": [{"columnSize": 12, "fieldNames": ["Text49810951"]}]}, {"dataLayoutColumns": [{"columnSize": 12, "fieldNames": ["Date80926909"]}]}, {"dataLayoutColumns": [{"columnSize": 12, "fieldNames": ["Text57935359"]}]}, {"dataLayoutColumns": [{"columnSize": 12, "fieldNames": ["RichText16440602"]}]}], "description": {"en_US": ""}, "title": {"en_US": ""}}], "dataRules": [], "description": {}, "name": {"en_US": "Team Members"}, "paginationMode": "single-page"}, "defaultLanguageId": "en_US", "description": {}, "name": {"en_US": "Team Members"}, "storageType": "default"}